DaShujuRumenZhinan2019/README.md
DaShujuRumenZhinan2019/__init__.py
DaShujuRumenZhinan2019/__main__.py
DaShujuRumenZhinan2019/file.epub
DaShujuRumenZhinan2019/index.html
DaShujuRumenZhinan2019/css/__init__.py
DaShujuRumenZhinan2019/css/annotations.css
DaShujuRumenZhinan2019/css/main.css
DaShujuRumenZhinan2019/css/normalize.css
DaShujuRumenZhinan2019/css/popup.css
DaShujuRumenZhinan2019/font/__init__.py
DaShujuRumenZhinan2019/font/fontello.eot
DaShujuRumenZhinan2019/font/fontello.svg
DaShujuRumenZhinan2019/font/fontello.ttf
DaShujuRumenZhinan2019/font/fontello.woff
DaShujuRumenZhinan2019/img/__init__.py
DaShujuRumenZhinan2019/img/annotator-glyph-sprite.png
DaShujuRumenZhinan2019/img/annotator-icon-sprite.png
DaShujuRumenZhinan2019/img/apple-touch-icon.png
DaShujuRumenZhinan2019/img/cancelfullscreen.png
DaShujuRumenZhinan2019/img/close.png
DaShujuRumenZhinan2019/img/fullscreen.png
DaShujuRumenZhinan2019/img/loader.gif
DaShujuRumenZhinan2019/img/menu-icon.png
DaShujuRumenZhinan2019/img/save.png
DaShujuRumenZhinan2019/img/saved.png
DaShujuRumenZhinan2019/img/settings-s.png
DaShujuRumenZhinan2019/img/settings.png
DaShujuRumenZhinan2019/img/star.png
DaShujuRumenZhinan2019/js/__init__.py
DaShujuRumenZhinan2019/js/epub.js
DaShujuRumenZhinan2019/js/epub.min.js
DaShujuRumenZhinan2019/js/epub.min.map
DaShujuRumenZhinan2019/js/hooks.min.js
DaShujuRumenZhinan2019/js/hooks.min.map
DaShujuRumenZhinan2019/js/reader.js
DaShujuRumenZhinan2019/js/reader.js.map
DaShujuRumenZhinan2019/js/reader.min.js
DaShujuRumenZhinan2019/js/reader.min.map
DaShujuRumenZhinan2019/js/hooks/__init__.py
DaShujuRumenZhinan2019/js/hooks/extensions/__init__.py
DaShujuRumenZhinan2019/js/hooks/extensions/highlight.js
DaShujuRumenZhinan2019/js/libs/__init__.py
DaShujuRumenZhinan2019/js/libs/jquery.min.js
DaShujuRumenZhinan2019/js/libs/localforage.min.js
DaShujuRumenZhinan2019/js/libs/screenfull.js
DaShujuRumenZhinan2019/js/libs/screenfull.min.js
DaShujuRumenZhinan2019/js/libs/zip.min.js
da_shuju_rumen_zhinan_2019-2024.3.4.0.dist-info/METADATA
da_shuju_rumen_zhinan_2019-2024.3.4.0.dist-info/WHEEL
da_shuju_rumen_zhinan_2019-2024.3.4.0.dist-info/entry_points.txt
da_shuju_rumen_zhinan_2019-2024.3.4.0.dist-info/top_level.txt
da_shuju_rumen_zhinan_2019-2024.3.4.0.dist-info/RECORD
